LICENSE
README.md
setup.cfg
setup.py
disspy/__init__.py
disspy/__main__.py
disspy/activity.py
disspy/app_commands.py
disspy/application.py
disspy/channel.py
disspy/client.py
disspy/embed.py
disspy/errors.py
disspy/guild.py
disspy/http.py
disspy/jsongenerators.py
disspy/payloads.py
disspy/reaction.py
disspy/state.py
disspy/typ.py
disspy/ui.py
disspy/user.py
disspy/utils.py
disspy/webhook.py
disspy.egg-info/PKG-INFO
disspy.egg-info/SOURCES.txt
disspy.egg-info/dependency_links.txt
disspy.egg-info/not-zip-safe
disspy.egg-info/requires.txt
disspy.egg-info/top_level.txt