Metadata-Version: 2.1
Name: disspy
Version: 0.7
Summary: Dispy - package for creating bots in discord written in Python
Home-page: https://github.com/itttgg/dispy
Author: itttgg
Author-email: aitiiigg1@gmail.com
License: UNKNOWN
Download-URL: https://github.com/itttgg/dispy/tree/0.7
Platform: UNKNOWN
Classifier: Programming Language :: Python :: 3
Classifier: Programming Language :: Python :: 3.8
Classifier: Programming Language :: Python :: 3.9
Classifier: Programming Language :: Python :: 3.10
Requires-Python: >=3.8
License-File: LICENSE
